LICENSE
README.md
setup.py
leetcli.egg-info/PKG-INFO
leetcli.egg-info/SOURCES.txt
leetcli.egg-info/dependency_links.txt
leetcli.egg-info/entry_points.txt
leetcli.egg-info/requires.txt
leetcli.egg-info/top_level.txt
src/__init__.py
src/main.py
src/commands/__init__.py
src/commands/daily.py
src/commands/edit.py
src/commands/list_problems.py
src/commands/login.py
src/commands/profile.py
src/commands/show.py
src/commands/solution.py
src/commands/submit.py
src/commands/test.py
src/lib/__init__.py
src/lib/problem_ui.py
src/lib/profile_ui.py
src/lib/solution_ui.py
src/lib/submission_ui.py
src/lib/welcome.py
src/server/__init__.py
src/server/api.py
src/server/auth.py
src/server/config.py
src/server/session_manager.py
src/server/solution_manager.py