Metadata-Version: 2.2
Name: leetcli
Version: 0.0.3
Summary: A sleek command-line tool for LeetCode platform
Home-page: https://github.com/yuvrajsinh5252/leetcode-cli
Author: Yuvrajsinh5252
Author-email: yuvrajsinh476@gmail.com
Classifier: Programming Language :: Python :: 3
Classifier: Operating System :: OS Independent
Requires-Python: >=3.6
License-File: LICENSE
Requires-Dist: setuptools
Requires-Dist: typer
Requires-Dist: requests
Requires-Dist: gql[all]
Requires-Dist: bs4
Requires-Dist: markdownify
Requires-Dist: rich
Dynamic: author
Dynamic: author-email
Dynamic: classifier
Dynamic: description
Dynamic: description-content-type
Dynamic: home-page
Dynamic: requires-dist
Dynamic: requires-python
Dynamic: summary
